setup.py
active_login_required/__init__.py
active_login_required/decorators.py
django_active_login_required.egg-info/PKG-INFO
django_active_login_required.egg-info/SOURCES.txt
django_active_login_required.egg-info/dependency_links.txt
django_active_login_required.egg-info/requires.txt
django_active_login_required.egg-info/top_level.txt
tests/__init__.py
tests/conftest.py
tests/models.py
tests/test_decorator.py
tests/urls.py
tests/views.py