Metadata-Version: 1.1
Name: django-active-login-required
Version: 0.1.2
Summary: Django view decorator that ensures a user is both active and authenticated
Home-page: http://github.com/mattdennewitz/django-active-login-required
Author: Matt Dennewitz
Author-email: mattdennewitz@gmail.com
License: UNKNOWN
Platform: UNKNOWN
Classifier: Development Status :: 5 - Production/Stable
Classifier: Intended Audience :: Developers
Classifier: License :: OSI Approved :: MIT License
Classifier: Programming Language :: Python
Classifier: Framework :: Django
